[
  {
    "title": "Test",
    "content": "Article content goes here........................................................................................................................................................................................................................................................................................................................................................................................................................................................................................................................................................................................................................................................................................................................................................................................................................................................................................................................................................................................................................................................................................................................",
    "author": "Iason",
    "imageUrl": "",
    "id": "1733591221006",
    "publishedDate": "2024-12-07T17:07:01.006Z"
  }
]